namedtreemap/__init__.py
namedtreemap-0.0.1.dist-info/METADATA
namedtreemap-0.0.1.dist-info/WHEEL
namedtreemap-0.0.1.dist-info/top_level.txt
namedtreemap-0.0.1.dist-info/RECORD
